pydeephaven_ticking/__init__.py
pydeephaven_ticking/_core.cpython-311-x86_64-linux-gnu.so
pydeephaven_ticking/_util.py
pydeephaven_ticking/py.typed
pydeephaven_ticking/table_listener.py
pydeephaven_ticking-41.1.dist-info/METADATA
pydeephaven_ticking-41.1.dist-info/WHEEL
pydeephaven_ticking-41.1.dist-info/top_level.txt
pydeephaven_ticking-41.1.dist-info/RECORD
